hessra_py-0.2.1.dist-info/METADATA
hessra_py-0.2.1.dist-info/WHEEL
hessra_py/__init__.py
hessra_py/hessra_py.pyd
hessra_py-0.2.1.dist-info/RECORD
