Metadata-Version: 2.4
Name: hessra-py
Version: 0.2.1
Classifier: Development Status :: 4 - Beta
Classifier: Intended Audience :: Developers
Classifier: License :: OSI Approved :: Apache Software License
Classifier: Programming Language :: Python :: 3
Classifier: Programming Language :: Python :: 3.8
Classifier: Programming Language :: Python :: 3.9
Classifier: Programming Language :: Python :: 3.10
Classifier: Programming Language :: Python :: 3.11
Classifier: Programming Language :: Python :: 3.12
Classifier: Programming Language :: Rust
Classifier: Topic :: Security
Classifier: Topic :: Security :: Cryptography
Classifier: Topic :: Software Development :: Libraries :: Python Modules
Classifier: Topic :: System :: Systems Administration :: Authentication/Directory
Requires-Dist: loguru>=0.7.3
Requires-Dist: pydantic>=2.10.6
Requires-Dist: pydantic-settings>=2.8.1
Summary: Python bindings for the Hessra authorization system with Biscuit token verification and mTLS support
Keywords: hessra,authorization,authentication,security,biscuit,mtls,token,verification,rust,cryptography
Author-email: Jake Valentic <jake@hessra.net>
License: Apache-2.0
Requires-Python: >=3.8
Project-URL: Homepage, https://github.com/hessra/hessra-sdk.rs
Project-URL: Repository, https://github.com/hessra/hessra-sdk.rs
Project-URL: Documentation, https://docs.rs/hessra-sdk
Project-URL: Bug Tracker, https://github.com/hessra/hessra-sdk.rs/issues
Project-URL: Source Code, https://github.com/hessra/hessra-sdk.rs/tree/main/hessra-py
